napari_pram/__init__.py
napari_pram/_reader.py
napari_pram/_sample_data.py
napari_pram/_widget.py
napari_pram/_writer.py
napari_pram/config.py
napari_pram/main_napari.py
napari_pram/napari.yaml
napari_pram/pram.py
napari_pram/utils.py
napari_pram/_tests/__init__.py
napari_pram/_tests/test_reader.py
napari_pram/_tests/test_sample_data.py
napari_pram/_tests/test_widget.py
napari_pram/_tests/test_writer.py
napari_pram-0.1.3.dist-info/LICENSE
napari_pram-0.1.3.dist-info/METADATA
napari_pram-0.1.3.dist-info/WHEEL
napari_pram-0.1.3.dist-info/entry_points.txt
napari_pram-0.1.3.dist-info/top_level.txt
napari_pram-0.1.3.dist-info/RECORD
